oze_dataset/__init__.py
oze_dataset/dataset.py
oze_dataset/labels.py
oze_dataset/utils.py
oze_dataset-1.0.1.dist-info/LICENSE
oze_dataset-1.0.1.dist-info/METADATA
oze_dataset-1.0.1.dist-info/WHEEL
oze_dataset-1.0.1.dist-info/top_level.txt
oze_dataset-1.0.1.dist-info/RECORD
