Metadata-Version: 2.1
Name: oze-dataset
Version: 1.0.1
Summary: Downloads oze dataset and creates npz file.
Home-page: https://github.com/krypton-unite/oze_dataset.git
Author: Daniel Kaminski de Souza
Author-email: daniel@kryptonunite.com
License: MIT
Download-URL: https://pypi.org/project/oze-dataset/
Keywords: Dataset,Oze Dataset,Time Series
Platform: UNKNOWN
Requires-Dist: time-series-dataset
Requires-Dist: pandas
Requires-Dist: lxml
Requires-Dist: requests
Requires-Dist: tqdm
Provides-Extra: dev
Requires-Dist: bumpversion ; extra == 'dev'
Requires-Dist: twine ; extra == 'dev'
Requires-Dist: wheel ; extra == 'dev'
Provides-Extra: test
Requires-Dist: pytest ; extra == 'test'
Requires-Dist: python-dotenv ; extra == 'test'
Requires-Dist: pytest-cov ; extra == 'test'
